README.md
setup.py
integrator/__init__.py
integrator.egg-info/PKG-INFO
integrator.egg-info/SOURCES.txt
integrator.egg-info/dependency_links.txt
integrator.egg-info/not-zip-safe
integrator.egg-info/top_level.txt
integrator/private/__init__.py
integrator/private/source_code.py